MANIFEST.in
setup.py
DtoTools.egg-info/PKG-INFO
DtoTools.egg-info/SOURCES.txt
DtoTools.egg-info/dependency_links.txt
DtoTools.egg-info/requires.txt
DtoTools.egg-info/top_level.txt
dtotools/__init__.py
dtotools/dto.py
dtotools/dto_type.py
dtotools/field.py
requirements/default.txt
requirements/test-2.6.txt
requirements/test.txt